yoruba_g2p/__init__.py
yoruba_g2p/cli.py
yoruba_g2p/core.py
yoruba_g2p-0.2.4.dist-info/licenses/LICENSE
yoruba_g2p-0.2.4.dist-info/METADATA
yoruba_g2p-0.2.4.dist-info/WHEEL
yoruba_g2p-0.2.4.dist-info/entry_points.txt
yoruba_g2p-0.2.4.dist-info/top_level.txt
yoruba_g2p-0.2.4.dist-info/RECORD
