Metadata-Version: 2.4
Name: yoruba-g2p
Version: 0.2.4
Summary: Yoruba grapheme-to-phoneme tool with tones (IPA + ASCII + MFA-ready).
Author-email: Opeyemi Osakuade <osakuadeopeyemi@gmail.com>
License: MIT
Project-URL: Homepage, https://github.com/OpeyemiOsakuade/yoruba-g2p
Project-URL: Documentation, https://github.com/OpeyemiOsakuade/yoruba-g2p
Project-URL: Source, https://github.com/OpeyemiOsakuade/yoruba-g2p
Project-URL: Issues, https://github.com/OpeyemiOsakuade/yoruba-g2p/issues
Keywords: g2p,grapheme-to-phoneme,yoruba,nlp,speech,ipa,tones,phonetics,mfa,pronunciation-dictionary
Classifier: Development Status :: 4 - Beta
Classifier: Intended Audience :: Science/Research
Classifier: Intended Audience :: Developers
Classifier: License :: OSI Approved :: MIT License
Classifier: Programming Language :: Python
Classifier: Programming Language :: Python :: 3
Classifier: Programming Language :: Python :: 3 :: Only
Classifier: Programming Language :: Python :: 3.10
Classifier: Programming Language :: Python :: 3.11
Classifier: Programming Language :: Python :: 3.12
Classifier: Topic :: Text Processing :: Linguistic
Classifier: Topic :: Scientific/Engineering :: Artificial Intelligence
Classifier: Topic :: Software Development :: Libraries :: Python Modules
Requires-Python: >=3.10
License-File: LICENSE
Requires-Dist: epitran>=1.22
Dynamic: license-file
